crispy/__init__.py
crispy/crisp.py
crispy/inversions.py
crispy/io.py
crispy/mixin.py
crispy/spectral.py
crispy/utils.py
crispy/visualisation.py
sst_crispy-1.0.2.dist-info/LICENSE
sst_crispy-1.0.2.dist-info/METADATA
sst_crispy-1.0.2.dist-info/WHEEL
sst_crispy-1.0.2.dist-info/top_level.txt
sst_crispy-1.0.2.dist-info/RECORD
