Metadata-Version: 2.1
Name: sst-crispy
Version: 1.0.2
Summary: A Python package for using data from the Swedish 1 m Solar Telescope's CRisp Imaging SpectroPolarimeter instrument.
Home-page: https://github.com/bionictoucan/crispy
Author: John Armstrong
Author-email: j.armstrong@strath.ac.uk
License: UNKNOWN
Platform: UNKNOWN
Classifier: Programming Language :: Python :: 3
Classifier: License :: OSI Approved :: MIT License
Classifier: Operating System :: OS Independent
Requires-Python: >3.6
License-File: LICENSE
Requires-Dist: numpy (<1.22,>1.19)
Requires-Dist: astropy
Requires-Dist: matplotlib
Requires-Dist: zarr
Requires-Dist: tqdm
Requires-Dist: cycler
Requires-Dist: specutils
Requires-Dist: numba (>0.55)
Requires-Dist: weno4
Requires-Dist: sunpy
Requires-Dist: ipywidgets
Requires-Dist: jupyterlab
